[{"purchaser":{"name":"Jane Doe","address":"jdoe@email.com","phoneNum":"1234567890"},"confNum":12345,"tickets":[{"performance":"West Side Story","seat":{"section":"Orchestra","row":"B","seatNum":12,"acessible":false,"inSeasonSection":false,"defaultPrice":29.99},"ticketStatus":2,"price":29.99},{"performance":"West Side Story","seat":{"section":"Orchestra","row":"B","seatNum":13,"acessible":false,"inSeasonSection":false,"defaultPrice":29.99},"ticketStatus":2,"price":29.99}],"perfDateTime":"2023-04-14T04:57:35.706Z"},{"purchaser":{"name":"kfjklae zcvzsedf","address":"oalpe@fkafp.c"},"confNum":338256896,"tickets":[{"performance":"Die Hardest","seat":{"section":"Orchestra","row":"G","seatNum":23,"inSeasonSection":false,"defaultPrice":74.99},"ticketStatus":1,"price":74.99},{"performance":"Die Hardest","seat":{"section":"Orchestra","row":"G","seatNum":24,"inSeasonSection":false,"defaultPrice":74.99},"ticketStatus":1,"price":74.99},{"performance":"Die Hardest","seat":{"section":"Orchestra","row":"G","seatNum":25,"inSeasonSection":false,"defaultPrice":74.99},"ticketStatus":1,"price":74.99}],"perfDateTime":"2023-04-30T22:00:00.000Z"},{"purchaser":{"name":"adgasdg aakhsdj","address":"jkalsdjf@lsjfg.com"},"confNum":638460928,"tickets":[{"performance":"Titanic 2: On Ice","seat":{"section":"Orchestra","row":"I","seatNum":22,"inSeasonSection":false,"defaultPrice":74.99},"ticketStatus":1,"price":74.99},{"performance":"Titanic 2: On Ice","seat":{"section":"Orchestra","row":"I","seatNum":23,"inSeasonSection":false,"defaultPrice":74.99},"ticketStatus":1,"price":74.99},{"performance":"Titanic 2: On Ice","seat":{"section":"Orchestra","row":"I","seatNum":24,"inSeasonSection":false,"defaultPrice":74.99},"ticketStatus":1,"price":74.99}],"perfDateTime":"2023-04-20T20:37:00.000Z"},{"purchaser":{"name":"khjdfsjk kuijeiwe","address":"lflf@pkfa.c"},"confNum":1526563840,"tickets":[{"performance":"East Side Saga","seat":{"section":"Riser3","row":"C","seatNum":3,"inSeasonSection":false,"defaultPrice":15.99},"ticketStatus":1,"price":15.99},{"performance":"East Side Saga","seat":{"section":"Riser3","row":"C","seatNum":5,"inSeasonSection":false,"defaultPrice":15.99},"ticketStatus":1,"price":15.99},{"performance":"East Side Saga","seat":{"section":"Riser3","row":"D","seatNum":4,"inSeasonSection":false,"defaultPrice":15.99},"ticketStatus":1,"price":15.99}],"perfDateTime":"2023-05-06T18:37:00.000Z"},{"purchaser":{"name":"ljasf sdflkjhadfj","address":"sfdk@f"},"confNum":338256896,"tickets":[{"performance":"Titanic 2: On Ice","seat":{"section":"Orchestra","row":"J","seatNum":22,"inSeasonSection":false,"defaultPrice":74.99},"ticketStatus":1,"price":74.99},{"performance":"Titanic 2: On Ice","seat":{"section":"Orchestra","row":"K","seatNum":23,"inSeasonSection":false,"defaultPrice":74.99},"ticketStatus":1,"price":74.99},{"performance":"Titanic 2: On Ice","seat":{"section":"Orchestra","row":"J","seatNum":24,"inSeasonSection":false,"defaultPrice":74.99},"ticketStatus":1,"price":74.99}],"perfDateTime":"2023-04-20T20:37:00.000Z"}]